{
   "title": "Leading crowdfunding platforms in the U.S. 2017 , by number of offerings",
   "xAxis": "Country",
   "yAxis": "Amount of offerings",
   "graphType": "bar",
   "summary": [
      "This statistic shows the Amount of their crowdfunding platforms in U.S. as of 2020 , 2017 Country . ",
      "In 2017 , Leading crowdfunding a total of 52 offerings in Wefunder ."
   ],
   "trends": [
      {},
      {
         "8": "1",
         "12": "0"
      }
   ],
   "data": [
      {
         "Country": "Wefunder",
         "Amount of offerings": "95"
      },
      {
         "Country": "Start Engine",
         "Amount of offerings": "52"
      },
      {
         "Country": "Seed Invest",
         "Amount of offerings": "29"
      },
      {
         "Country": "uFunding",
         "Amount of offerings": "18"
      },
      {
         "Country": "Dream Funded",
         "Amount of offerings": "14"
      },
      {
         "Country": "TruCrowd",
         "Amount of offerings": "13"
      },
      {
         "Country": "Nextseed",
         "Amount of offerings": "13"
      },
      {
         "Country": "Net Capital",
         "Amount of offerings": "12"
      },
      {
         "Country": "Microventures",
         "Amount of offerings": "11"
      },
      {
         "Country": "Jumpstart Micro",
         "Amount of offerings": "10"
      },
      {
         "Country": "Flashfunders",
         "Amount of offerings": "9"
      },
      {
         "Country": "Republic",
         "Amount of offerings": "9"
      },
      {
         "Country": "GridShare",
         "Amount of offerings": "7"
      },
      {
         "Country": "Growth Fountain",
         "Amount of offerings": "5"
      },
      {
         "Country": "Venture.co",
         "Amount of offerings": "4"
      },
      {
         "Country": "Crowd Source Funded",
         "Amount of offerings": "3"
      },
      {
         "Country": "FundingWonder",
         "Amount of offerings": "2"
      },
      {
         "Country": "ibankers",
         "Amount of offerings": "2"
      },
      {
         "Country": "Local Stake",
         "Amount of offerings": "1"
      },
      {
         "Country": "Open Night Capital",
         "Amount of offerings": "1"
      }
   ]
}