{
   "title": "Global basketball shoe sales 2012 - 2013 , by NBA player",
   "labels": [
      "Quarter",
      "2012",
      "2013"
   ],
   "columnType": "multi",
   "graphType": "bar",
   "summary": [
      "This statistic shows a projection with the global revenues of basketball shoe sales in the third Quarter of 2012 and the third Quarter of 2013 . ",
      "In the third Quarter of 2013 , 2012 accounted for 2000 % of global SoC shoe revenues ."
   ],
   "trends": [
      {},
      {
         "10": [
            "0",
            "1"
         ]
      }
   ],
   "data": [
      {
         "Quarter": "Michael Jordan",
         "2012": "2000",
         "2013": "2500"
      },
      {
         "Quarter": "Lebron James",
         "2012": "300",
         "2013": "300"
      },
      {
         "Quarter": "Kevin Durant",
         "2012": "35",
         "2013": "175"
      },
      {
         "Quarter": "Kobe Bryant",
         "2012": "50",
         "2013": "50"
      },
      {
         "Quarter": "Derrick Rose",
         "2012": "40",
         "2013": "40"
      }
   ],
   "gold": "This timeline depicts global basketball shoe sales in 2012 and 2013 , by NBA player . In 2013 , Michael Jordan and his shoe brand , Jordan , earned approximately 2.5 billion U.S. dollars .\n"
}