{
   "title": "Dentists : number practicing in Europe in 2017 , by country",
   "xAxis": "Country",
   "yAxis": "Number of employees",
   "columnType": "two",
   "graphType": "bar",
   "summaryType": "nlp",
   "summary": [
      "This statistic displays the Number of employees working at the Dentists Europe practicing in 2017 , Country . ",
      "According to the source , Germany had the highest Number of employees , with 70445 thousand people ."
   ],
   "trends": [
      {},
      {
         "5": "0",
         "14": "0"
      }
   ],
   "data": [
      {
         "Country": "Germany",
         "Number of employees": "70445"
      },
      {
         "Country": "Italy",
         "Number of employees": "49552"
      },
      {
         "Country": "France",
         "Number of employees": "43167"
      },
      {
         "Country": "United Kingdom",
         "Number of employees": "34760"
      },
      {
         "Country": "Poland",
         "Number of employees": "13331"
      },
      {
         "Country": "Belgium",
         "Number of employees": "8516"
      },
      {
         "Country": "Sweden",
         "Number of employees": "8077"
      },
      {
         "Country": "Czechia",
         "Number of employees": "7921"
      },
      {
         "Country": "Hungary",
         "Number of employees": "6589"
      },
      {
         "Country": "Austria",
         "Number of employees": "5009"
      },
      {
         "Country": "Norway",
         "Number of employees": "4590"
      },
      {
         "Country": "Denmark",
         "Number of employees": "4247"
      },
      {
         "Country": "Switzerland",
         "Number of employees": "4217"
      },
      {
         "Country": "Lithuania",
         "Number of employees": "2839"
      },
      {
         "Country": "Slovenia",
         "Number of employees": "1455"
      },
      {
         "Country": "Latvia",
         "Number of employees": "1380"
      },
      {
         "Country": "Estonia",
         "Number of employees": "1265"
      },
      {
         "Country": "Luxembourg",
         "Number of employees": "581"
      }
   ],
   "gold": "In 2017 , there were over 70 thousand practicing dentists in Germany , the highest number recorded in Europe . Followed by Italy with almost 50 thousand dentists and then France with around 43.1 thousand . As these countries have some of the highest populations in the European Union , it is follows that they have the highest number of practicing dentists .\n"
}