{
   "title": "Urbanization in South Africa 2018",
   "xAxis": "Year",
   "yAxis": "Share of urban population in total population",
   "columnType": "two",
   "graphType": "line",
   "summary": [
      "This statistic shows the degree of Urbanization in South Africa from 2008 to 2018 . ",
      "Urbanization means the Share of urban population in the total population of a country . ",
      "In 2018 , 66.36 % of South Africa 's total population lived in urban areas and cities ."
   ],
   "trends": [
      {
         "10": "10",
         "12": "0"
      },
      {},
      {
         "1": "0",
         "3": "0"
      }
   ],
   "data": [
      {
         "Year": "2018",
         "Share of urban population in total population": "66.36"
      },
      {
         "Year": "2017",
         "Share of urban population in total population": "65.85"
      },
      {
         "Year": "2016",
         "Share of urban population in total population": "65.34"
      },
      {
         "Year": "2015",
         "Share of urban population in total population": "64.83"
      },
      {
         "Year": "2014",
         "Share of urban population in total population": "64.31"
      },
      {
         "Year": "2013",
         "Share of urban population in total population": "63.79"
      },
      {
         "Year": "2012",
         "Share of urban population in total population": "63.27"
      },
      {
         "Year": "2011",
         "Share of urban population in total population": "62.75"
      },
      {
         "Year": "2010",
         "Share of urban population in total population": "62.22"
      },
      {
         "Year": "2009",
         "Share of urban population in total population": "61.69"
      },
      {
         "Year": "2008",
         "Share of urban population in total population": "61.15"
      }
   ]
}