{
   "title": "Number of road deaths in Germany 2006 to 2018\n",
   "xAxis": "Year",
   "yAxis": "Number of fatalities",
   "columnType": "two",
   "graphType": "line",
   "summaryType": "baseline",
   "summary": [
      "This line chart has an x axis representing Year and a y axis representing Number of fatalities, with a total of 13 data points. The chart has 4 significant trends.",
      " The longest trend is slightly negative which exists from 2011 to 2006.",
      " But, the next significant trend is moderately negative which exists from 2018 to 2015.",
      " On the other hand, the next significant trend is extremely positive which exists from 2015 to 2013.",
      " Also, the next significant trend is slightly negative which exists from 2013 to 2011."
   ],
   "trends": [
      {},
      {
         "1": "7",
         "12": "12"
      },
      {
         "3": "0",
         "14": "3"
      },
      {
         "3": "3",
         "14": "5"
      },
      {
         "3": "5",
         "14": "7"
      }
   ],
   "data": [
      {
         "Year": "2018",
         "Number of fatalities": 3275.0
      },
      {
         "Year": "2017",
         "Number of fatalities": 3180.0
      },
      {
         "Year": "2016",
         "Number of fatalities": 3206.0
      },
      {
         "Year": "2015",
         "Number of fatalities": 3459.0
      },
      {
         "Year": "2014",
         "Number of fatalities": 3377.0
      },
      {
         "Year": "2013",
         "Number of fatalities": 3339.0
      },
      {
         "Year": "2012",
         "Number of fatalities": 3600.0
      },
      {
         "Year": "2011",
         "Number of fatalities": 4009.0
      },
      {
         "Year": "2010",
         "Number of fatalities": 3648.0
      },
      {
         "Year": "2009",
         "Number of fatalities": 4152.0
      },
      {
         "Year": "2008",
         "Number of fatalities": 4477.0
      },
      {
         "Year": "2007",
         "Number of fatalities": 4949.0
      },
      {
         "Year": "2006",
         "Number of fatalities": 5091.0
      }
   ],
   "gold": "This line graph shows the number of road traffic fatalities per year in Germany between 2006 and 2018 . In 2009 , 4,152 individuals were killed in motor vehicle accidents . An overall decrease in the number of road deaths was observed within the time period shown .\n"
}