{
   "title": "Construction cost per kilometer of high-speed line in France 2014\n",
   "xAxis": "High-speed Line",
   "yAxis": "Construction cost per kilometer in millions of euros",
   "columnType": "two",
   "graphType": "bar",
   "summary": [
      "This bar chart has 8 categories for the x axis representing High-speed Line, and a y axis representing Construction cost per kilometer in millions of euros.",
      " The highest category is found at LGV_Mediterranean where Construction cost per kilometer in millions of euros is 19.7.",
      " The lowest category is found at LGV_Paris-Lyon where Construction cost per kilometer in millions of euros is 5.5."
   ],
   "trends": {
      "maxIndex": 7,
      "minIndex": 0
   },
   "data": [
      {
         "High-speed Line": "LGV Paris-Lyon",
         "Construction cost per kilometer in millions of euros": 5.5
      },
      {
         "High-speed Line": "LGV Atlantic",
         "Construction cost per kilometer in millions of euros": 10.4
      },
      {
         "High-speed Line": "LGV North",
         "Construction cost per kilometer in millions of euros": 10.8
      },
      {
         "High-speed Line": "LGV Rh\u00f4ne-Alpes",
         "Construction cost per kilometer in millions of euros": 13.4
      },
      {
         "High-speed Line": "North-South interconnection",
         "Construction cost per kilometer in millions of euros": 15.5
      },
      {
         "High-speed Line": "LGV East",
         "Construction cost per kilometer in millions of euros": 15.7
      },
      {
         "High-speed Line": "LGV Rhine-Rhone",
         "Construction cost per kilometer in millions of euros": 17.5
      },
      {
         "High-speed Line": "LGV Mediterranean",
         "Construction cost per kilometer in millions of euros": 19.7
      }
   ]
}